ihunt/__init__.py
ihunt/__main__.py
ihunt/cli.py
ihunt/gather.py
ihunt/models.py
ihunt/querytype.py
ihunt/stdout.py
ihunt/utils.py
ihunt/version.py
ihunt/api/abuseipdb.py
ihunt/api/alienvault.py
ihunt/api/anubis.py
ihunt/api/duckduckgo.py
ihunt/api/emailrep.py
ihunt/api/eva.py
ihunt/api/gemini.py
ihunt/api/groq.py
ihunt/api/hackertarget.py
ihunt/api/hunter.py
ihunt/api/ip_api.py
ihunt/api/ipapi.py
ihunt/api/pulsedive.py
ihunt/api/robtex.py
ihunt/api/subdomaincenter.py
ihunt/api/urldna.py
ihunt/api/virustotal.py
ihunt/api/whoisxml.py
ihunt/cmds/dig.py
ihunt/cmds/whois.py
ihunt-0.1.8.dist-info/METADATA
ihunt-0.1.8.dist-info/WHEEL
ihunt-0.1.8.dist-info/entry_points.txt
ihunt-0.1.8.dist-info/licenses/LICENSE
ihunt-0.1.8.dist-info/RECORD
