Metadata-Version: 2.3
Name: ihunt
Version: 0.1.8
Summary: Information gathering tool.
Author-email: hdks <hdks.bug@gmail.com>
Requires-Python: >=3.12
Requires-Dist: click>=8.1.7
Requires-Dist: colorama>=0.4.6
Requires-Dist: duckduckgo-search>=6.2.9
Requires-Dist: google-generativeai>=0.7.2
Requires-Dist: groq>=0.10.0
Requires-Dist: python-dotenv>=1.0.1
Requires-Dist: pyyaml>=6.0.2
Requires-Dist: requests>=2.32.3
